pyorm/__init__.py
pyorm/db_manager.py
pyorm/entity.py
pyorm/utils.py
tests/__init__.py
tests/test_db_manager.py
PyORM_Lite-1.0.0.dist-info/LICENSE
PyORM_Lite-1.0.0.dist-info/METADATA
PyORM_Lite-1.0.0.dist-info/WHEEL
PyORM_Lite-1.0.0.dist-info/top_level.txt
PyORM_Lite-1.0.0.dist-info/RECORD
