Metadata-Version: 2.1
Name: PyORM-Lite
Version: 1.0.0
Summary: A lightweight Python ORM for SQLite databases.
Home-page: https://github.com/sby-devapp/PyORM.git
Author: sby-devapp
Author-email: sbydev.app@gmail.com
Classifier: Programming Language :: Python :: 3
Classifier: License :: OSI Approved :: MIT License
Classifier: Operating System :: OS Independent
Requires-Python: >=3.7
License-File: LICENSE
